antchain_sdk_ms/__init__.py
antchain_sdk_ms/client.py
antchain_sdk_ms/models.py
antchain_ms-3.4.0.dist-info/LICENSE
antchain_ms-3.4.0.dist-info/METADATA
antchain_ms-3.4.0.dist-info/WHEEL
antchain_ms-3.4.0.dist-info/top_level.txt
antchain_ms-3.4.0.dist-info/RECORD
